navmenu/__init__.py
navmenu/actions.py
navmenu/contents.py
navmenu/deserializer.py
navmenu/item_contents.py
navmenu/items.py
navmenu/keyboard.py
navmenu/menu_manager.py
navmenu/menus.py
navmenu/responses.py
navmenu/state.py
navmenu/io/__init__.py
navmenu/io/base.py
navmenu/io/console.py
navmenu/io/telegram.py
navmenu/io/vk.py
navmenu-0.3.0.dist-info/LICENSE
navmenu-0.3.0.dist-info/METADATA
navmenu-0.3.0.dist-info/WHEEL
navmenu-0.3.0.dist-info/top_level.txt
navmenu-0.3.0.dist-info/RECORD
