Metadata-Version: 2.1
Name: navmenu
Version: 0.3.0
Summary: A library to create multilevel menus for chatbots
Home-page: https://github.com/rashidsh/navmenu
Author: rashidsh
Author-email: mail@rashidsh.ru
License: MIT
Platform: UNKNOWN
Classifier: Development Status :: 3 - Alpha
Classifier: Intended Audience :: Developers
Classifier: License :: OSI Approved :: MIT License
Classifier: Operating System :: OS Independent
Classifier: Programming Language :: Python :: 3
Classifier: Programming Language :: Python :: 3.6
Classifier: Programming Language :: Python :: 3.7
Classifier: Programming Language :: Python :: 3.8
Classifier: Programming Language :: Python :: 3.9
Requires-Python: >=3.6
License-File: LICENSE
